opurva/__init__.py
opurva/messaging_response/__init__.py
opurva/rest/__init__.py
opurva/voice_response/__init__.py
opurva-1.0.0.dist-info/licenses/LICENSE
opurva-1.0.0.dist-info/METADATA
opurva-1.0.0.dist-info/WHEEL
opurva-1.0.0.dist-info/top_level.txt
opurva-1.0.0.dist-info/RECORD
